ediwheel/__init__.py
ediwheel/connector.py
ediwheel/templates/inquiry.xml
ediwheel/templates/inquiry_batch.xml
ediwheel-0.4.0.dist-info/LICENSE
ediwheel-0.4.0.dist-info/METADATA
ediwheel-0.4.0.dist-info/WHEEL
ediwheel-0.4.0.dist-info/top_level.txt
ediwheel-0.4.0.dist-info/RECORD
