Metadata-Version: 2.1
Name: ediwheel
Version: 0.4.0
Summary: AdHoc Ediwheel XML API port to Python
Author-email: "M.Ranzetti" <maloranzetti@gmail.com>
Project-URL: Homepage, https://github.com/mrztti/python-ediwheel
Project-URL: Bug Tracker, https://github.com/mrztti/python-ediwheel/issues
Classifier: Programming Language :: Python :: 3
Classifier: License :: OSI Approved :: MIT License
Classifier: Operating System :: OS Independent
Requires-Python: >=3.10
License-File: LICENSE
